stellarismodparser/__init__.py
stellarismodparser/stellarismodparser.py
stellarismodparser-1.0.7.dist-info/LICENSE
stellarismodparser-1.0.7.dist-info/METADATA
stellarismodparser-1.0.7.dist-info/WHEEL
stellarismodparser-1.0.7.dist-info/top_level.txt
stellarismodparser-1.0.7.dist-info/RECORD
