Metadata-Version: 2.1
Name: stellarismodparser
Version: 1.0.7
Summary: Parse Stellaris's mod descriptor files.
Author-email: cswimr <seaswimmerthefsh@gmail.com>
Project-URL: Homepage, https://www.coastalcommits.com/cswimr/stellarismodparser
Project-URL: Issues, https://www.coastalcommits.com/cswimr/stellarismodparser/issues
Classifier: Programming Language :: Python :: 3
Classifier: License :: OSI Approved :: MIT License
Classifier: Operating System :: OS Independent
Requires-Python: >=3.9
License-File: LICENSE
Requires-Dist: semver >=3.0.2
